[
  {
    "name": "sonar-cag",
    "transport": "stdio",
    "command": "sonar-context-augmentation",
    "args": [],
    "env": {},
    "inherits": ["SONARQUBE_URL", "SONARQUBE_TOKEN", "SONARQUBE_ORG", "SONARQUBE_PROJECT_KEY", "SONAR_SQ_BRANCH", "SONAR_WORKSPACE_DIR", "SONAR_LOG_LEVEL", "DUMP_UDG", "TELEMETRY_DISABLED"],
    "supportedTransports": ["stdio"],
    "instructions": "## Context Augmentation\nYour SonarQube organization has Context Augmentation enabled. Use these\ntools to obtain precise, structured answers about the project instead\nof file reading or text search.\n\n### Guidelines and dependencies\n- `get_guidelines`: MUST call before writing or editing source code.\n  Use `mode=\"combined\"` with `categories` (e.g. \"Complexity &\n  Maintainability\", \"Naming & Code Style\"), `languages`, and `file_paths`.\n- `check_dependency`: MUST call before adding or upgrading any dependency\n  in a manifest or lockfile.\n\n### Architecture (Java, JavaScript, TypeScript, Python, C#)\nMUST use these when reasoning about module boundaries or dependencies;\ndo not infer structure from build files or imports.\n- `get_current_architecture`: inspect the module or package dependency\n  graph at a chosen depth.\n- `get_intended_architecture`: inspect allowed/forbidden module couplings.\n  MUST call before introducing or changing a cross-module dependency.\n\n### Code navigation (Java only)\nWhenever you would grep, search, or read a Java file to find, read, or\ntrace code, MUST use these tools instead.\n- `search_by_signature_patterns`: find declarations by name, modifier,\n  or annotation.\n- `search_by_body_patterns`: find usages by regex in method bodies.\n- `get_source_code`: read the signature and body of a specific FQN.\n- `get_upstream_call_flow`: find callers of a method (e.g. refactor\n  impact, entry-point auditing, trigger tracing).\n- `get_downstream_call_flow`: find callees of a method (e.g. execution\n  flow, downstream impact).\n- `get_references`: list inbound and outbound references of a class,\n  interface, or module (not methods). Use for class-level coupling.\n- `get_type_hierarchy`: walk the inheritance tree of classes,\n  interfaces, enums, or records.\n"
  }
]
